{
  "todos": [
    {
      "title": "first item",
      "completed": false,
      "id": "0415013137"
    },
    {
      "title": "second item",
      "completed": false,
      "id": "0595467753"
    },
    {
      "title": "item_0",
      "completed": false,
      "id": "3474503066"
    },
    {
      "title": "item_1",
      "completed": false,
      "id": "9955882214"
    },
    {
      "title": "item_2",
      "completed": false,
      "id": "7113699820"
    },
    {
      "title": "item_3",
      "completed": false,
      "id": "1287412276"
    },
    {
      "title": "item_4",
      "completed": false,
      "id": "9658337228"
    }
  ]
}